multiple_video_files_duration/__init__.py
multiple_video_files_duration/duration.py
multiple_video_files_duration-0.0.5.dist-info/LICENSE
multiple_video_files_duration-0.0.5.dist-info/METADATA
multiple_video_files_duration-0.0.5.dist-info/WHEEL
multiple_video_files_duration-0.0.5.dist-info/top_level.txt
multiple_video_files_duration-0.0.5.dist-info/RECORD
